Metadata-Version: 1.0
Name: publish-aws-lambda
Version: 0.4.3
Summary: Publish a Python module as a set of AWS lambda functions
Home-page: https://github.com/ophirh/publish-aws-lambda
Author: Ophir
Author-email: opensource@itculate.io
License: MIT
Keywords: aws,lambda,publish
Platform: UNKNOWN
